rovlib/__init__.py
rovlib/cameras.py
rovlib/control.py
rovlib-1.1.0.dist-info/LICENSE
rovlib-1.1.0.dist-info/METADATA
rovlib-1.1.0.dist-info/WHEEL
rovlib-1.1.0.dist-info/top_level.txt
rovlib-1.1.0.dist-info/RECORD
