Metadata-Version: 2.1
Name: rovlib
Version: 1.1.0
Summary: ROV control and image library by RobEn
Home-page: https://github.com/RobEn-AAST
Author: karimkohel, abbashabib, mhwahdan
Author-email: <kareemkohel@gmail.com>
Keywords: python,video,stream,video stream,camera stream,sockets,mavlink,rov,control,ardusub
Classifier: Development Status :: 5 - Production/Stable
Classifier: Intended Audience :: Education
Classifier: Natural Language :: English
Classifier: Operating System :: OS Independent
Classifier: License :: OSI Approved :: MIT License
Classifier: Programming Language :: Python :: 3.6
Classifier: Programming Language :: Python :: 3.7
Classifier: Programming Language :: Python :: 3.8
Classifier: Programming Language :: Python :: 3.9
Requires-Python: >=3.6
License-File: LICENSE
Requires-Dist: opencv-python
Requires-Dist: pymavlink
